Metadata-Version: 2.1
Name: clip-benchmark
Version: 1.6.2
Summary: CLIP-like models benchmarks on various datasets
Home-page: https://github.com/mehdidc/clip_benchmark
Author: Mehdi Cherti
Author-email: mehdicherti@gmail.com
License: MIT license
Keywords: clip_benchmark
Platform: UNKNOWN
Classifier: Development Status :: 2 - Pre-Alpha
Classifier: Intended Audience :: Developers
Classifier: License :: OSI Approved :: MIT License
Classifier: Natural Language :: English
Classifier: Programming Language :: Python :: 3
Classifier: Programming Language :: Python :: 3.6
Classifier: Programming Language :: Python :: 3.7
Classifier: Programming Language :: Python :: 3.8
Requires-Python: >=3.6
Requires-Dist: torch>=1.8.1
Requires-Dist: torchvision>=0.8.9
Requires-Dist: tqdm>=2
Requires-Dist: scikit-learn<2,>=1.0
Requires-Dist: open-clip-torch>=0.2.1
Requires-Dist: pycocoevalcap
Requires-Dist: webdataset>=0.2.31
Requires-Dist: transformers
